odoo/addons/base_user_show_email/README.rst
odoo/addons/base_user_show_email/__init__.py
odoo/addons/base_user_show_email/__manifest__.py
odoo/addons/base_user_show_email/i18n/base_user_show_email.pot
odoo/addons/base_user_show_email/readme/CONTRIBUTORS.rst
odoo/addons/base_user_show_email/readme/DESCRIPTION.rst
odoo/addons/base_user_show_email/static/description/icon.png
odoo/addons/base_user_show_email/static/description/index.html
odoo/addons/base_user_show_email/views/login_layout.xml
odoo/addons/base_user_show_email/views/res_users_view.xml
odoo13_addon_base_user_show_email-13.0.1.0.1.dev3.dist-info/METADATA
odoo13_addon_base_user_show_email-13.0.1.0.1.dev3.dist-info/WHEEL
odoo13_addon_base_user_show_email-13.0.1.0.1.dev3.dist-info/top_level.txt
odoo13_addon_base_user_show_email-13.0.1.0.1.dev3.dist-info/RECORD
